pypi_def/__init__.py
pypi_def/module1.py
pypi_def/module2.py
pypi_def/subpackage1/__init__.py
pypi_def/subpackage1/module3.py
pypi_def/subpackage1/module4.py
pypi_def/subpackage2/__init__.py
pypi_def/subpackage2/module5.py
pypi_def-0.0.2.dist-info/LICENSE
pypi_def-0.0.2.dist-info/METADATA
pypi_def-0.0.2.dist-info/WHEEL
pypi_def-0.0.2.dist-info/top_level.txt
pypi_def-0.0.2.dist-info/RECORD
