Metadata-Version: 2.1
Name: pypi-def
Version: 0.0.2
Summary: Contoh Library Python dengan Def.
Home-page: https://github.com/novay/pypi-def
Author: Novianto Rahmadi
Author-email: novay@btekno.id
License: MIT
Classifier: Intended Audience :: Developers
Classifier: License :: OSI Approved :: MIT License
Classifier: Programming Language :: Python
Classifier: Programming Language :: Python :: 3
Classifier: Programming Language :: Python :: 3.6
Classifier: Programming Language :: Python :: 3.7
Classifier: Programming Language :: Python :: 3.8
Classifier: Programming Language :: Python :: 3.9
Classifier: Operating System :: OS Independent
License-File: LICENSE
